sa_filter/__init__.py
sa_filter/sa_filter.py
sa_filter/data/alert_collection.csv
sa_filter-1.0.0.dist-info/licenses/LICENSE
sa_filter-1.0.0.dist-info/METADATA
sa_filter-1.0.0.dist-info/WHEEL
sa_filter-1.0.0.dist-info/top_level.txt
sa_filter-1.0.0.dist-info/RECORD
