Metadata-Version: 2.4
Name: sa-filter
Version: 1.0.0
Summary: Identify structural alerts using the RDKit and ChEMBL.
Author-email: "Olivier J.M. Béquignon" <olivier.bequignon.maintainer@gmail.com>
Maintainer-email: "Olivier J.M. Béquignon" <olivier.bequignon.maintainer@gmail.com>
Project-URL: Homepage, https://github.com/OlivierBeq/sa_filter
Keywords: PAINS,structural alerts,filtering,cheminformatics,molecule,chemistry
Classifier: Programming Language :: Python
Classifier: Programming Language :: Python :: 3
Classifier: Programming Language :: Python :: 3.10
Classifier: Programming Language :: Python :: 3.11
Classifier: Programming Language :: Python :: 3.12
Classifier: Operating System :: OS Independent
Classifier: Topic :: Scientific/Engineering :: Chemistry
Requires-Python: >=3.10
License-File: LICENSE
Requires-Dist: pandas
Requires-Dist: rdkit
Provides-Extra: testing
Requires-Dist: pytest; extra == "testing"
Dynamic: license-file
